algomanim/__init__.py
algomanim/assets/__init__.py
algomanim/assets/svg/__init__.py
algomanim/assets/svg/arrows/radius_x10.svg
algomanim/assets/svg/arrows/radius_x12.svg
algomanim/assets/svg/arrows/radius_x14.svg
algomanim/assets/svg/arrows/radius_x16.svg
algomanim/assets/svg/arrows/radius_x18.svg
algomanim/assets/svg/arrows/radius_x20.svg
algomanim/assets/svg/arrows/template.svg
algomanim/core/__init__.py
algomanim/core/base.py
algomanim/core/code_block_base.py
algomanim/core/linear_container.py
algomanim/core/rectangle_cells.py
algomanim/datastructures/__init__.py
algomanim/datastructures/array.py
algomanim/datastructures/linked_list.py
algomanim/datastructures/string.py
algomanim/examples/README.md
algomanim/examples/examples.py
algomanim/examples/rend_no_poetry.sh
algomanim/examples/rend_poetry.sh
algomanim/examples/video_output/high_quality/.gitkeep
algomanim/examples/video_output/low_quality/.gitkeep
algomanim/examples/video_output/medium_quality/.gitkeep
algomanim/helpers/__init__.py
algomanim/helpers/datastructures.py
algomanim/ui/__init__.py
algomanim/ui/code_block.py
algomanim/ui/relative_text.py
algomanim/ui/titles.py
algomanim-0.5.0.dist-info/LICENSE
algomanim-0.5.0.dist-info/METADATA
algomanim-0.5.0.dist-info/WHEEL
algomanim-0.5.0.dist-info/RECORD
