Metadata-Version: 2.3
Name: algomanim
Version: 0.5.0
Summary: Manim-powered algorithm tasks visualizations for LeetCode and beyond
License: MIT
Author: Benedict Abub
Author-email: fkhurkhd2123dfs@tutamail.com
Requires-Python: >=3.9
Classifier: License :: OSI Approved :: MIT License
Classifier: Programming Language :: Python :: 3
Classifier: Programming Language :: Python :: 3.9
Classifier: Programming Language :: Python :: 3.10
Classifier: Programming Language :: Python :: 3.11
Classifier: Programming Language :: Python :: 3.12
Classifier: Programming Language :: Python :: 3.13
Requires-Dist: manim (>=0.19.0)
Requires-Dist: pyperclip (>=1.11.0,<2.0.0)
Project-URL: Homepage, https://github.com/benabub/algomanim
Project-URL: Repository, https://github.com/benabub/algomanim
